{
  "dialogueID": "bag",
  "displayName": "Bag",
  "startNodeID": "",
  "startNodeConditions": [
    {
      "nodeID": "start1",
      "flagEvaluationLogic": 0,
      "flagRequirements": [
        {
          "flagName": "bag-grabbed",
          "requiredValue": false
        }
      ]
    }
  ],
  "nodes": [
    {
      "nodeID": "start1",
      "speakerID": "Rafa",
      "dialogueTextKey": "I can fit so many things in here!",
      "portraitSprite": null,
      "portraitGif": null,
      "portraitSpritePath": "",
      "portraitGifPath": "Data/Gifs/mc_idle",
      "animationTrigger": "",
      "choices": [],
      "nextNodeID": "2",
      "conditions": [],
      "effects": [
        {
          "effectType": 1,
          "flagName": "bag-grabbed",
          "flagValue": true,
          "itemID": "",
          "itemQuantity": 0,
          "questID": "",
          "questNewState": "",
          "animationName": "",
          "eventName": "",
          "customEffectType": "",
          "customParameters": []
        }
      ],
      "autoAdvanceDelay": 0.0,
      "textSpeed": 100.0
    },
    {
      "nodeID": "2",
      "speakerID": "",
      "dialogueTextKey": "You can now click on the bag icon to access your inventory!",
      "portraitSprite": null,
      "portraitGif": null,
      "portraitSpritePath": "",
      "portraitGifPath": "",
      "animationTrigger": "",
      "choices": [],
      "nextNodeID": "",
      "conditions": [],
      "effects": [],
      "autoAdvanceDelay": 0.0,
      "textSpeed": 100.0
    }
  ],
  "localizationTable": "Dialogue"
}

